README
setup.py
bin/linkbot-serialid-tool.py
linkbot_serialid_tool/__init__.py
linkbot_serialid_tool/dialog.py
linkbot_serialid_tool/linkbot_serialid_tool.py
linkbot_serialid_tool.egg-info/PKG-INFO
linkbot_serialid_tool.egg-info/SOURCES.txt
linkbot_serialid_tool.egg-info/dependency_links.txt
linkbot_serialid_tool.egg-info/not-zip-safe
linkbot_serialid_tool.egg-info/requires.txt
linkbot_serialid_tool.egg-info/top_level.txt