Metadata-Version: 1.0
Name: linkbot-serialid-tool
Version: 0.1.2
Summary: Tool for programming Linkbot serial IDs
Home-page: UNKNOWN
Author: David Ko
Author-email: david@barobo.com
License: UNKNOWN
Platform: UNKNOWN
